fastmsg/__init__.py
fastmsg/test_message.py
fastmsg-1.0.0.dist-info/METADATA
fastmsg-1.0.0.dist-info/WHEEL
fastmsg-1.0.0.dist-info/top_level.txt
fastmsg-1.0.0.dist-info/RECORD
