Metadata-Version: 2.1
Name: fastmsg
Version: 1.0.0
Summary: Set of minimalistic cross-language serialization libraries for C++ / Go / Python
Requires-Python: >=3.8
Provides-Extra: dev
Requires-Dist: black ; extra == 'dev'
Requires-Dist: isort ; extra == 'dev'
Requires-Dist: pytest ; extra == 'dev'
Requires-Dist: pytest-cov ; extra == 'dev'
Requires-Dist: radon ; extra == 'dev'
Requires-Dist: xenon ; extra == 'dev'
